{
  "analysis_metadata": {
    "tool": "Ghidra MCP",
    "date": "2026-03-07",
    "target": "Menace Tactical Game Binary",
    "focus": "Buff/Boost EventHandler System Analysis"
  },
  "namespaces": {
    "ai_behaviors": "Menace.Tactical.AI.Behaviors",
    "skill_effects": "Menace.Tactical.Skills.Effects",
    "tile_effects": "Menace.Tactical.TileEffects",
    "core_tactical": "Menace.Tactical"
  },
  "buff_behavior_system": {
    "class": "Menace.Tactical.AI.Behaviors.Buff",
    "base_class": "SkillBehavior",
    "functions": {
      "constructor": {
        "address": "0x180726e00",
        "description": "Initializes buff behavior data structures",
        "fields": {
          "0x60": "List<Assist_Data> - Stores assist targets and scores",
          "0x68": "List<Tile> - Candidate tiles for buffing",
          "0x70": "HashSet<Tile> - Valid target tiles",
          "0x78": "HashSet<Tile> - Excluded/processed tiles"
        }
      },
      "GetTargetValue": {
        "address": "0x18072be30",
        "description": "Calculates utility value for buffing a target",
        "parameters": [
          "param_1: Buff instance",
          "param_2: Unknown",
          "param_3: Skill reference",
          "param_4: Target tile"
        ],
        "buff_type_flags": {
          "0x1": "Suppression reduction buff",
          "0x2": "Morale boost buff",
          "0x8000": "Morale restore to max",
          "0x10000": "Movement assist buff",
          "0x20000": "Threat awareness buff",
          "0x40000": "Cover bonus buff"
        },
        "ai_config_offsets": {
          "0x170": "BuffWeight - Base behavior weight multiplier",
          "0x174": "BuffValueMultiplier - Final value scaling",
          "0x178": "TileUtilityMult - Tile position bonus",
          "0x17C": "SuppressionBuffMult - Suppression reduction value",
          "0x180": "MoraleBoostMult - Morale boost value",
          "0x184": "MoraleRestoreMult - Morale restore value",
          "0x188": "MovementAssistMult - Movement buff value",
          "0x18C": "ThreatAwarenessMult - Threat tracking value",
          "0x190": "ThreatValue - Accumulated threat score"
        }
      },
      "GetUtilityFromTileMult": {
        "address": "0x18072cbf0",
        "description": "Returns tile utility multiplier from AIConfig at offset 0x178"
      },
      "OnScaleBehaviorWeight": {
        "address": "0x18072cc60",
        "description": "Scales behavior weight using AIConfig multiplier at offset 0x170"
      }
    },
    "data_factory": {
      "class": "Menace.Tactical.AI.Behaviors.Data.Buff",
      "method": "CreateBehavior",
      "address": "0x180753640"
    }
  },
  "assist_behavior": {
    "class": "Menace.Tactical.AI.Behaviors.Assist",
    "functions": {
      "OnEvaluate": {
        "address": "0x180724440",
        "description": "Evaluates assist opportunities for allied units"
      },
      "GetHighestScoredTarget": {
        "address": "0x180724200",
        "description": "Returns best assist target from evaluation"
      }
    },
    "data_structure": {
      "name": "Assist.Data",
      "fields": {
        "0x00": "Tile reference - Target tile",
        "0x08": "Float score - Assist utility value"
      }
    }
  },
  "suppression_system": {
    "inflict_suppression_behavior": {
      "class": "Menace.Tactical.AI.Behaviors.InflictSuppression",
      "functions": {
        "GetTargetValue": {
          "address": "0x18072deb0",
          "description": "Evaluates suppression infliction value with targetType=1"
        },
        "GetUtilityFromTileMult": {
          "address": "0x18072df90"
        },
        "OnScaleBehaviorWeight": {
          "address": "0x18072e000"
        },
        "constructor": {
          "address": "0x18072e0e0"
        }
      }
    },
    "change_suppression_handler": {
      "class": "Menace.Tactical.Skills.Effects.ChangeSuppressionHandler",
      "functions": {
        "Apply": {
          "address": "0x180700600",
          "description": "Applies suppression change to target",
          "template_offsets": {
            "0x5C": "SuppressionAmount - Amount to change",
            "0x60": "UseOwner flag - Apply to owner instead of target"
          }
        },
        "OnAdded": {
          "address": "0x180700720"
        },
        "OnApply": {
          "address": "0x180700760"
        }
      }
    },
    "suppression_handler": {
      "class": "Menace.Tactical.Skills.Effects.SuppressionHandler",
      "functions": {
        "OnRoundStart": "0x18071f790",
        "OnUpdate": "0x18071ff90",
        "UpdateBehavior": "0x180720150"
      }
    },
    "actor_methods": {
      "ApplySuppression": {
        "address": "0x1805ddda0",
        "description": "Main suppression application with discipline modifier",
        "entity_flags": {
          "bit_5": "Suppression immunity flag",
          "bit_6": "Alternative suppression handling"
        }
      },
      "ChangeSuppressionAndUpdateAP": {
        "address": "0x1805de3b0"
      },
      "GetSuppressionPct": {
        "address": "0x1805df710"
      },
      "SetSuppression": {
        "address": "0x1805e76d0"
      }
    },
    "events": {
      "OnSuppressionApplied": {
        "add": "0x180678770",
        "remove": "0x18067a030",
        "invoke": "0x1806725b0"
      }
    }
  },
  "morale_system": {
    "change_morale_handler": {
      "class": "Menace.Tactical.Skills.Effects.ChangeMoraleHandler",
      "functions": {
        "ApplyMorale": {
          "address": "0x1806fdd20",
          "description": "Applies morale change to target",
          "modes": {
            "2": "Set to half of max morale",
            "3": "Set to max morale"
          },
          "direction_flags": {
            "1": "Max direction - Don't lower if already above target",
            "2": "Min direction - Don't raise if already below target"
          }
        },
        "OnAdded": {
          "address": "0x1806fddd0"
        },
        "OnApply": {
          "address": "0x1806fde10"
        }
      }
    },
    "attack_morale_handler": {
      "class": "Menace.Tactical.Skills.Effects.AttackMoraleHandler",
      "functions": {
        "ApplyMorale": "0x1806fbb70",
        "OnApply": "0x1806fbc50"
      }
    },
    "actor_methods": {
      "ApplyMorale": {
        "address": "0x1805dd240",
        "description": "Applies morale change with immunity and multiplier checks",
        "field_checks": {
          "actor[9]": "IsAlive flag",
          "actor+0x16A": "Morale lock flag",
          "properties+0xEC bit 7": "Morale immunity",
          "properties+0xA8": "Morale type mask",
          "properties+0xBC": "Morale multiplier"
        }
      },
      "GetMoralePct": {
        "address": "0x1805df4a0"
      },
      "GetMoraleMax": {
        "address": "0x1805df330"
      },
      "SetMorale": {
        "address": "0x1805e7150"
      }
    },
    "events": {
      "OnMoraleStateChanged": {
        "add": "0x180677dd0",
        "remove": "0x180679690",
        "invoke": "0x1806716b0"
      }
    }
  },
  "rally_handler": {
    "class": "Menace.Tactical.Skills.Effects.RallyHandler",
    "address": "0x1807182e0",
    "description": "Reduces suppression on allied actors within range",
    "template_offsets": {
      "0x58": "Base suppression reduction amount",
      "0x5C": "Falloff per tile distance"
    },
    "formula": "reduction = base - (distance - 1) * falloff, min 0"
  },
  "regeneration_handler": {
    "class": "Menace.Tactical.Skills.Effects.RegenerationHandler",
    "functions": {
      "ApplyEffect": {
        "address": "0x180719340",
        "description": "Main healing function",
        "template_offsets": {
          "0x58": "ApplicationTiming (2=OnApply)",
          "0x5C": "HealPercentage - Fraction of max HP to restore",
          "0x60": "Audio ID for healing sound",
          "0x68": "Visual effect prefab reference"
        },
        "formula": "newHP = currentHpPct + (maxHp * healPercentage), clamped to 1.0"
      },
      "OnApply": {
        "address": "0x180719640"
      },
      "OnTurnStart": {
        "address": "0x1807196c0"
      },
      "OnTurnEnd": {
        "address": "0x180719680"
      }
    }
  },
  "add_skill_handler": {
    "class": "Menace.Tactical.Skills.Effects.AddSkillHandler",
    "description": "Adds skills/buffs to target entities",
    "functions": {
      "OnApply": {
        "address": "0x1806e5730",
        "template_offsets": {
          "0x58": "Event timing (0=OnApply)",
          "0x60": "SkillToAdd template reference",
          "0x68": "OnlyApplyOnHit flag"
        },
        "skill_fields_set": {
          "0xE8": "CasterActor - Who applied the skill",
          "0xF0": "SourceSkill - Parent skill reference"
        }
      },
      "AddSkillToSelf": {
        "address": "0x1806e53a0"
      },
      "IsApplicableTo": {
        "address": "0x1806e5560"
      },
      "OnAdded": {
        "address": "0x1806e5700"
      },
      "OnRemoved": {
        "address": "0x1806e5c70"
      },
      "OnTargetHit": {
        "address": "0x1806e5cd0"
      }
    }
  },
  "status_effect_tile_handler": {
    "class": "Menace.Tactical.TileEffects.ApplyStatusEffectTileEffectHandler",
    "functions": {
      "OnEnter": {
        "address": "0x1806853a0",
        "description": "Applies status effect when entity enters tile",
        "template_offsets": {
          "0xB8": "StatusEffectTemplate - Skill template to apply",
          "0xC0": "RequiredTags - Entity must have at least one",
          "0xC8": "ExcludedTags - Entity must not have any"
        }
      },
      "OnLeave": {
        "address": "0x1806855b0"
      },
      "AppendTooltipData": {
        "address": "0x180685270"
      }
    }
  },
  "skill_event_handler_base": {
    "class": "Menace.Tactical.Skills.SkillEventHandler",
    "description": "Base class for all skill effect handlers",
    "functions": {
      "GetActor": {
        "address": "0x1806eef20",
        "description": "Returns actor associated with skill"
      },
      "GetEntity": {
        "address": "0x1806eef40",
        "description": "Returns entity associated with skill"
      },
      "GetOwner": {
        "address": "0x1806eef60",
        "description": "Returns owner from skill's container"
      }
    },
    "field_layout": {
      "0x10": "BaseSkill reference",
      "0x18": "Effect template data"
    }
  },
  "skill_add_event_handler": {
    "class": "Menace.Tactical.Skills.Skill",
    "function": "AddEventHandler",
    "address": "0x1806d4230",
    "description": "Registers handler in skill's handler array",
    "parameters": {
      "param_1": "Skill instance",
      "param_2": "Handler to add",
      "param_3": "Handler index in array"
    },
    "flags_set": {
      "0x50": "hasOverride - Handler overrides base method",
      "0x9A": "isChargeHandler - Handler is ChargeHandler type"
    }
  },
  "skill_behavior_base": {
    "class": "Menace.Tactical.AI.SkillBehavior",
    "description": "Base class for AI skill-related behaviors",
    "functions": {
      "GetTargetValue": {
        "address": "0x180733460",
        "description": "Comprehensive target evaluation including damage, morale, suppression"
      },
      "ConsiderSkillSpecifics": {
        "address": "0x180733100"
      },
      "HandleDeployAndSetup": {
        "address": "0x1807352a0"
      },
      "OnExecute": {
        "address": "0x180735630"
      },
      "OnReset": {
        "address": "0x180735860"
      },
      "constructor": {
        "address": "0x180735880"
      }
    }
  },
  "tactical_manager_events": {
    "class": "Menace.Tactical.TacticalManager",
    "buff_related_events": {
      "OnSkillAdded": {
        "invoke": "0x1806725b0 (via InvokeOnSkillAdded)"
      },
      "OnSuppressionApplied": {
        "invoke": "0x1806725b0"
      },
      "OnMoraleStateChanged": {
        "invoke": "0x1806716b0"
      },
      "OnHitpointsChanged": {
        "invoke": "Referenced in RegenerationHandler with code 1000"
      }
    }
  },
  "ai_config_buff_fields": {
    "description": "AIConfig singleton fields controlling buff behavior values",
    "base_offset": "Accessed via TypeInfo+0xB8 -> Instance+0x8",
    "fields": {
      "0x170": "BuffBehaviorWeight",
      "0x174": "BuffValueMultiplier",
      "0x178": "TileUtilityMultiplier",
      "0x17C": "SuppressionBuffValue",
      "0x180": "MoraleBoostValue",
      "0x184": "MoraleRestoreValue",
      "0x188": "MovementBuffValue",
      "0x18C": "ThreatAwarenessValue",
      "0x190": "ThreatAccumulationValue",
      "0xE4": "DamageMultiplier",
      "0xE8": "ArmorValueMultiplier",
      "0xEC": "MoraleEventValue",
      "0xF0": "ElementKillValue",
      "0xF8": "ThreatBonusMultiplier",
      "0xFC": "LimitedUsesThreshold"
    }
  },
  "entity_properties_flags": {
    "description": "Entity property flags affecting buff application",
    "offset_0xEC": {
      "bit_1": "IsVehicle",
      "bit_5": "SuppressionImmune",
      "bit_6": "AlternateSuppressionHandling",
      "bit_7": "MoraleImmune"
    },
    "offset_0xA8": "MoraleTypeMask - Which morale events affect this entity",
    "offset_0xBC": "MoraleMultiplier - Scales morale changes"
  },
  "constants_and_multipliers": {
    "data_addresses": {
      "DAT_182d8fb9c": "1.0f - Standard multiplier",
      "DAT_182d8fbfc": "0.5f - Half multiplier",
      "DAT_182d8fc24": "0.75f - Quarter penalty",
      "DAT_182d8fd48": "1.5f - 150% bonus",
      "DAT_182d8fbd8": "0.01f - Discipline multiplier",
      "DAT_182d8fc2c": "2.0f - Double multiplier",
      "DAT_182d8fc44": "3.0f - Triple threshold",
      "DAT_182d8ffe4": "0.25f - Quarter multiplier",
      "DAT_182d8fd40": "0.5f - Half morale",
      "DAT_182d8ff80": "Suppression damage formula coefficient"
    }
  },
  "aura_system": {
    "emit_aura_handler": {
      "class": "Menace.Tactical.Skills.Effects.EmitAuraHandler",
      "description": "Emits aura buffs to nearby allied entities",
      "functions": {
        "OnEntitySpawned": {
          "address": "0x1807051b0",
          "description": "Triggered when new entity spawns - applies aura to allied units",
          "template_offsets": {
            "0x58": "SkillTemplate - Aura skill to apply to allies",
            "0x60": "ExcludeSelf flag - Whether to skip aura origin"
          }
        },
        "OnMissionStarted": {
          "address": "0x1807054a0"
        },
        "OnMissionFinished": {
          "address": "0x1807053e0"
        }
      }
    },
    "change_property_aura_handler": {
      "class": "Menace.Tactical.Skills.Effects.ChangePropertyAuraHandler",
      "description": "Applies property modifications based on distance from aura origin",
      "functions": {
        "OnUpdate": {
          "address": "0x1806fe1f0",
          "description": "Core aura logic - iterates PropertyChange array",
          "template_offsets": {
            "0x58": "PropertyChange[] array - Properties to modify",
            "0x60": "MaxRange - Maximum distance for aura effect",
            "0x64": "LinearFalloff flag - Apply distance-based scaling"
          },
          "property_change_structure": {
            "0x00": "PropertyType enum (4 bytes)",
            "0x04": "PropertyValue (4 bytes)",
            "0x08": "Multiplier float (4 bytes)"
          }
        },
        "IsEnabled": {
          "address": "0x1806fe110"
        },
        "ValidateOrigin": {
          "address": "0x1806fe450"
        }
      }
    }
  },
  "handler_inheritance_hierarchy": {
    "SkillEventHandler": {
      "children": [
        "ChangeSuppressionHandler",
        "ChangeMoraleHandler",
        "AttackMoraleHandler",
        "RallyHandler",
        "RegenerationHandler",
        "AddSkillHandler",
        "SpawnTileEffectHandler",
        "ChargeHandler",
        "EmitAuraHandler",
        "ChangePropertyAuraHandler"
      ]
    },
    "TileEffectHandler": {
      "children": [
        "ApplyStatusEffectTileEffectHandler",
        "ApplySkillTileEffectHandler"
      ]
    },
    "SkillBehavior (AI)": {
      "children": [
        "Buff",
        "Assist",
        "InflictSuppression",
        "RemoveStatusEffect"
      ]
    }
  }
}
